glc/__init__.py
glc/lexer.py
glc/main.py
glc/parser.py
glc/t2c.py
goatlang-0.0.2.dist-info/METADATA
goatlang-0.0.2.dist-info/WHEEL
goatlang-0.0.2.dist-info/entry_points.txt
goatlang-0.0.2.dist-info/top_level.txt
goatlang-0.0.2.dist-info/RECORD
