Metadata-Version: 2.4
Name: goatlang
Version: 0.0.2
Summary: A language for goated people with no purpose.
Author-email: Naren <narendrkumarsuresh@gmail.com>
License-Expression: MIT
Requires-Python: >=3.8
